decloud_trainer/__init__.py
decloud_trainer/cli.py
decloud_trainer/config.py
decloud_trainer/ipfs.py
decloud_trainer/trainer.py
decloud_trainer/training.py
decloud_trainer_kit-0.1.0.dist-info/METADATA
decloud_trainer_kit-0.1.0.dist-info/WHEEL
decloud_trainer_kit-0.1.0.dist-info/entry_points.txt
decloud_trainer_kit-0.1.0.dist-info/top_level.txt
decloud_trainer_kit-0.1.0.dist-info/RECORD
