Metadata-Version: 2.4
Name: decloud-trainer-kit
Version: 0.1.0
Summary: DECLOUD Trainer Kit - Train models and earn rewards
Author: DECLOUD Team
Requires-Python: >=3.8
Requires-Dist: torch>=2.0.0
Requires-Dist: torchvision>=0.15.0
Requires-Dist: requests>=2.28.0
Dynamic: author
Dynamic: requires-dist
Dynamic: requires-python
Dynamic: summary
